agp_bindings-0.3.5.dist-info/METADATA
agp_bindings-0.3.5.dist-info/WHEEL
agp_bindings/_agp_bindings.pyi
agp_bindings/__init__.py
agp_bindings/_agp_bindings.cp313-win_amd64.pyd
agp_bindings-0.3.5.dist-info/RECORD
