Metadata-Version: 2.4
Name: agp-bindings
Version: 0.3.5
Classifier: Development Status :: 3 - Alpha
Classifier: Intended Audience :: Developers
Classifier: Topic :: Software Development :: Libraries
Classifier: Programming Language :: Python :: 3.9
Classifier: Programming Language :: Python :: 3.10
Classifier: Programming Language :: Python :: 3.11
Classifier: Programming Language :: Python :: 3.12
Classifier: Programming Language :: Python :: 3.13
Summary: AGP Rust bindings for Python
License: Apache-2.0
Requires-Python: >=3.9, <4.0
Project-URL: Repository, https://github.com/agntcy/agp
Project-URL: Issues, https://github.com/agntcy/agp/issues
Project-URL: Changelog, https://github.com/agntcy/agp/blob/main/data-plane/python-bindings/CHANGELOG.md
